.testr.conf
AUTHORS
CONTRIBUTING.rst
ChangeLog
LICENSE
README.rst
requirements.txt
setup.cfg
setup.py
test-requirements.txt
tox.ini
lpmqtt/__init__.py
lpmqtt/daemon.py
lpmqtt/lp.py
lpmqtt.egg-info/PKG-INFO
lpmqtt.egg-info/SOURCES.txt
lpmqtt.egg-info/dependency_links.txt
lpmqtt.egg-info/entry_points.txt
lpmqtt.egg-info/not-zip-safe
lpmqtt.egg-info/pbr.json
lpmqtt.egg-info/requires.txt
lpmqtt.egg-info/top_level.txt
lpmqtt/tests/__init__.py