Metadata-Version: 1.1
Name: lpmqtt
Version: 0.0.1
Summary: Publish Launchpad Event Stream on MQTT
Home-page: UNKNOWN
Author: Matthew Treinish
Author-email: mtreinish@kortar.org
License: UNKNOWN
Platform: UNKNOWN
Classifier: Intended Audience :: Information Technology
Classifier: Intended Audience :: System Administrators
Classifier: Intended Audience :: Developers
Classifier: License :: OSI Approved :: Apache Software License
Classifier: Operating System :: POSIX :: Linux
Classifier: Programming Language :: Python
Classifier: Programming Language :: Python :: 2
Classifier: Programming Language :: Python :: 2.7
Classifier: Programming Language :: Python :: 3
Classifier: Programming Language :: Python :: 3.4
